odoo/addons/hr_employee_cost_history/README.rst
odoo/addons/hr_employee_cost_history/__init__.py
odoo/addons/hr_employee_cost_history/__manifest__.py
odoo/addons/hr_employee_cost_history/i18n/es.po
odoo/addons/hr_employee_cost_history/i18n/fr.po
odoo/addons/hr_employee_cost_history/i18n/hr_employee_cost_history.pot
odoo/addons/hr_employee_cost_history/i18n/it.po
odoo/addons/hr_employee_cost_history/models/__init__.py
odoo/addons/hr_employee_cost_history/models/hr_employee.py
odoo/addons/hr_employee_cost_history/models/hr_employee_timesheet_cost_history.py
odoo/addons/hr_employee_cost_history/readme/CONTRIBUTORS.md
odoo/addons/hr_employee_cost_history/readme/DESCRIPTION.md
odoo/addons/hr_employee_cost_history/readme/USAGE.md
odoo/addons/hr_employee_cost_history/security/ir.model.access.csv
odoo/addons/hr_employee_cost_history/static/description/icon.png
odoo/addons/hr_employee_cost_history/static/description/index.html
odoo/addons/hr_employee_cost_history/tests/__init__.py
odoo/addons/hr_employee_cost_history/tests/test_hr_timesheet.py
odoo/addons/hr_employee_cost_history/views/hr_employee_timesheet_cost_history_views.xml
odoo/addons/hr_employee_cost_history/views/hr_employee_views.xml
odoo/addons/hr_employee_cost_history/wizards/__init__.py
odoo/addons/hr_employee_cost_history/wizards/hr_employee_timesheet_cost_wizard.py
odoo/addons/hr_employee_cost_history/wizards/hr_employee_timesheet_cost_wizard_views.xml
odoo_addon_hr_employee_cost_history-18.0.1.0.0.3.dist-info/METADATA
odoo_addon_hr_employee_cost_history-18.0.1.0.0.3.dist-info/WHEEL
odoo_addon_hr_employee_cost_history-18.0.1.0.0.3.dist-info/top_level.txt
odoo_addon_hr_employee_cost_history-18.0.1.0.0.3.dist-info/RECORD
