Metadata-Version: 2.1
Name: odoo-addon-hr_employee_cost_history
Version: 18.0.1.0.0.3
Requires-Python: >=3.10
Requires-Dist: freezegun
Requires-Dist: odoo==18.0.*
Summary: Adds an history to employee's costs.
Home-page: https://github.com/OCA/timesheet
License: LGPL-3
Author: Moduon, Odoo Community Association (OCA)
Author-email: support@odoo-community.org
Classifier: Programming Language :: Python
Classifier: Framework :: Odoo
Classifier: Framework :: Odoo :: 18.0
Classifier: License :: OSI Approved :: GNU Lesser General Public License v3 (LGPLv3)
Classifier: Development Status :: 4 - Beta
